{
  "scene_results": [
    {
      "scID": 31,
      "snt": [
        {
          "id": 0,
          "vlc": []
        },
        {
          "id": 1,
          "vlc": []
        },
        {
          "id": 2,
          "vlc": []
        },
        {
          "id": 3,
          "vlc": []
        },
        {
          "id": 4,
          "vlc": []
        },
        {
          "id": 5,
          "vlc": []
        },
        {
          "id": 6,
          "vlc": [
            {
              "label": "DRUGS_MENTION_NON_DETAILED",
              "conf": 85
            }
          ]
        },
        {
          "id": 7,
          "vlc": []
        },
        {
          "id": 8,
          "vlc": []
        },
        {
          "id": 9,
          "vlc": []
        },
        {
          "id": 10,
          "vlc": []
        },
        {
          "id": 11,
          "vlc": []
        }
      ]
    }
  ]
}